actions/__init__.py
actions/clean_dir/__init__.py
actions/clean_dir/cli.py
actions/clean_dir/constants.py
actions/clean_dir/lib.py
actions/cli.py
actions/constants.py
actions/publish_package/__init__.py
actions/publish_package/cli.py
actions/publish_package/constants.py
actions/publish_package/lib.py
actions/py.typed
actions/random_sleep/__init__.py
actions/random_sleep/cli.py
actions/random_sleep/constants.py
actions/random_sleep/lib.py
actions/re_encrypt/__init__.py
actions/re_encrypt/cli.py
actions/re_encrypt/constants.py
actions/re_encrypt/lib.py
actions/register_gitea_runner/__init__.py
actions/register_gitea_runner/cli.py
actions/register_gitea_runner/configs/config.yml
actions/register_gitea_runner/configs/entrypoint.sh
actions/register_gitea_runner/constants.py
actions/register_gitea_runner/lib.py
actions/setup_cronjob/__init__.py
actions/setup_cronjob/cli.py
actions/setup_cronjob/configs/cron.tmpl
actions/setup_cronjob/configs/logrotate.tmpl
actions/setup_cronjob/constants.py
actions/setup_cronjob/lib.py
actions/tag_commit/__init__.py
actions/tag_commit/cli.py
actions/tag_commit/constants.py
actions/tag_commit/lib.py
actions/utilities.py
dycw_actions-0.16.13.dist-info/WHEEL
dycw_actions-0.16.13.dist-info/entry_points.txt
dycw_actions-0.16.13.dist-info/METADATA
dycw_actions-0.16.13.dist-info/RECORD
