Metadata-Version: 2.3
Name: dycw-actions
Version: 0.16.13
Summary: Library of actions
Requires-Dist: click>=8.3.1
Requires-Dist: dycw-utilities>=0.188.3
Requires-Dist: pydantic>=2.12.5
Requires-Dist: requests>=2.32.5
Requires-Dist: ruamel-yaml>=0.19.1
Requires-Dist: xdg-base-dirs>=6.0.2
Requires-Dist: click==8.3.1 ; extra == 'cli'
Requires-Dist: dycw-utilities==0.188.3 ; extra == 'cli'
Requires-Dist: pydantic==2.12.5 ; extra == 'cli'
Requires-Dist: requests==2.32.5 ; extra == 'cli'
Requires-Dist: ruamel-yaml==0.19.1 ; extra == 'cli'
Requires-Dist: xdg-base-dirs==6.0.2 ; extra == 'cli'
Requires-Python: >=3.12
Provides-Extra: cli
